{
  "description": "An action to move the camera by **dragging** with the mouse (or **scrolling** with the touch), on vertical, horizontal or both directions.",
  "extensionNamespace": "",
  "fullName": "Drag Camera With Pointer",
  "name": "DragCameraWithPointer",
  "shortDescription": "An action to move the camera by dragging with the mouse (or scrolling with the touch), on vertical, horizontal or both directions.",
  "tags": "pointer, drag, camera, scroll, gestures",
  "version": "1.0.0",
  "url": "Extensions/DragCameraWithPointer.json",
  "headerUrl": "Extensions/DragCameraWithPointer-header.json"
}
